abserdes/__init__.py
abserdes/datatype.py
abserdes/deserializeuserinput.py
abserdes/instanceattrs.py
abserdes/serialize.py
abserdes/serializer.py
abserdes/serializerutils.py
abserdes/strcast.py
abserdes/userinputnode.py
abserdes-2.8.dist-info/LICENSE
abserdes-2.8.dist-info/METADATA
abserdes-2.8.dist-info/WHEEL
abserdes-2.8.dist-info/top_level.txt
abserdes-2.8.dist-info/RECORD
