Metadata-Version: 2.1
Name: abserdes
Version: 2.8
Summary: A Basic Serializer and Deserializer that makes XMLserialization and deserialization in Python absurdly easy.
Home-page: https://github.com/astokely/abserdes
Author: Andy Stokely
Author-email: amstokely@ucsd.edu
License: MIT
Keywords: xml,serialize,deserialize,serializer
Platform: Linux
Platform: Unix
Requires-Python: >=3.8
License-File: LICENSE
Requires-Dist: numpy
Requires-Dist: pytest
Requires-Dist: data-science-types
Requires-Dist: cython
